kbackup/__init__.py
kbackup/__main__.py
kbackup/backup.py
kbackup/cli.py
kbackup/helper.py
kbackup-0.2.1.dist-info/licenses/LICENSE
kbackup-0.2.1.dist-info/METADATA
kbackup-0.2.1.dist-info/WHEEL
kbackup-0.2.1.dist-info/entry_points.txt
kbackup-0.2.1.dist-info/top_level.txt
kbackup-0.2.1.dist-info/RECORD
