Metadata-Version: 2.4
Name: kbackup
Version: 0.2.1
Summary: kubernetes manifest backup with well-structured folder
Author: Ahmad Bayhaqi
License-Expression: Apache-2.0
Project-URL: Homepage, https://github.com/Kyuubang/kbackup
Project-URL: Changelog, https://github.com/Kyuubang/kbackup/releases
Project-URL: Issues, https://github.com/Kyuubang/kbackup/issues
Project-URL: CI, https://github.com/Kyuubang/kbackup/actions
Requires-Python: >=3.10
License-File: LICENSE
Requires-Dist: click
Requires-Dist: kubernetes
Requires-Dist: jq
Provides-Extra: test
Requires-Dist: pytest; extra == "test"
Dynamic: license-file
